colander_data_converter/__init__.py
colander_data_converter/py.typed
colander_data_converter/base/__init__.py
colander_data_converter/base/common.py
colander_data_converter/base/models.py
colander_data_converter/base/utils.py
colander_data_converter/base/types/__init__.py
colander_data_converter/base/types/actor.py
colander_data_converter/base/types/artifact.py
colander_data_converter/base/types/base.py
colander_data_converter/base/types/data_fragment.py
colander_data_converter/base/types/detection_rule.py
colander_data_converter/base/types/device.py
colander_data_converter/base/types/event.py
colander_data_converter/base/types/observable.py
colander_data_converter/base/types/threat.py
colander_data_converter/converters/__init__.py
colander_data_converter/converters/misp/__init__.py
colander_data_converter/converters/misp/converter.py
colander_data_converter/converters/misp/models.py
colander_data_converter/converters/misp/utils.py
colander_data_converter/converters/misp/data/actor_misp_mapping.json
colander_data_converter/converters/misp/data/artifact_misp_mapping.json
colander_data_converter/converters/misp/data/data_fragment_misp_mapping.json
colander_data_converter/converters/misp/data/detection_rule_misp_mapping.json
colander_data_converter/converters/misp/data/device_misp_mapping.json
colander_data_converter/converters/misp/data/event_misp_mapping.json
colander_data_converter/converters/misp/data/observable_misp_mapping.json
colander_data_converter/converters/misp/data/relation_misp_mapping.json
colander_data_converter/converters/misp/data/threat_misp_mapping.json
colander_data_converter/converters/misp/definitions/colander-data-fragment/definition.json
colander_data_converter/converters/misp/definitions/colander-event/definition.json
colander_data_converter/converters/stix2/__init__.py
colander_data_converter/converters/stix2/converter.py
colander_data_converter/converters/stix2/mapping.py
colander_data_converter/converters/stix2/models.py
colander_data_converter-1.0.7.dist-info/METADATA
colander_data_converter-1.0.7.dist-info/WHEEL
colander_data_converter-1.0.7.dist-info/licenses/LICENSE
colander_data_converter-1.0.7.dist-info/RECORD
