Metadata-Version: 2.4
Name: colander-data-converter
Version: 1.0.7
Summary: A set of helpers to manipulate Colander data.
Project-URL: discord, https://discord.gg/qGX73GYNdp
Project-URL: documentation, https://pts-project.org/colander-data-converter/
Project-URL: donate, https://opencollective.com/pts
Project-URL: homepage, https://pts-project.org
Project-URL: issues, https://github.com/PiRogueToolSuite/colander-data-converter/issues
Project-URL: mastodon, https://infosec.exchange/@pts
Project-URL: repository, https://github.com/PiRogueToolSuite/colander-data-converter
Author-email: U+039b <hello@pts-project.org>
Maintainer-email: U+039b <hello@pts-project.org>
License-Expression: GPL-3.0-or-later
License-File: LICENSE
Classifier: Programming Language :: Python :: 3 :: Only
Classifier: Programming Language :: Python :: 3.12
Classifier: Programming Language :: Python :: 3.13
Requires-Python: >=3.12
Requires-Dist: docutils-stubs==0.0.22
Requires-Dist: jinja2==3.1.6
Requires-Dist: pydantic==2.11.7
Requires-Dist: pymisp>=2.5.17
Requires-Dist: types-docutils==0.22.1.20250923
